reccd/__init__.py
reccd/__main__.py
reccd/arguments.py
reccd/entrypoint.py
reccd/aio/__init__.py
reccd/aio/connection.py
reccd/apps/__init__.py
reccd/apps/client.py
reccd/apps/modules.py
reccd/apps/server.py
reccd/argparse/__init__.py
reccd/argparse/namespace_utils.py
reccd/argparse/typing_namespace.py
reccd/chrono/__init__.py
reccd/chrono/datetime.py
reccd/conversion/__init__.py
reccd/conversion/to_boolean.py
reccd/daemon/__init__.py
reccd/daemon/daemon_answer.py
reccd/daemon/daemon_client.py
reccd/daemon/daemon_servicer.py
reccd/inspect/__init__.py
reccd/inspect/type_origin.py
reccd/logging/__init__.py
reccd/logging/colored_formatter.py
reccd/logging/logging.py
reccd/memory/__init__.py
reccd/memory/shared_memory_queue.py
reccd/memory/shared_memory_utils.py
reccd/memory/shared_memory_validator.py
reccd/module/__init__.py
reccd/module/errors.py
reccd/module/module.py
reccd/module/mixin/__init__.py
reccd/module/mixin/_module_base.py
reccd/module/mixin/module_doc.py
reccd/module/mixin/module_open.py
reccd/module/mixin/module_register.py
reccd/module/mixin/module_router.py
reccd/module/mixin/module_version.py
reccd/network/__init__.py
reccd/network/address_family.py
reccd/package/__init__.py
reccd/package/package_utils.py
reccd/packet/__init__.py
reccd/packet/content_helper.py
reccd/packet/content_packer.py
reccd/packet/content_parameter.py
reccd/packet/content_unpacker.py
reccd/parse/__init__.py
reccd/parse/cfg_parse.py
reccd/parse/env_parse.py
reccd/proto/__init__.py
reccd/proto/daemon/__init__.py
reccd/proto/daemon/daemon_api_pb2.py
reccd/proto/daemon/daemon_api_pb2_grpc.py
reccd/regex/__init__.py
reccd/regex/access_filter.py
reccd/route/__init__.py
reccd/route/dynamic_resource.py
reccd/system/__init__.py
reccd/system/environ.py
reccd/system/path_context.py
reccd/uri/__init__.py
reccd/uri/host_port.py
reccd/uri/rpc_uri.py
reccd/uri/uds.py
reccd/variables/__init__.py
reccd/variables/aio.py
reccd/variables/argparse.py
reccd/variables/config.py
reccd-1.0.3.dist-info/LICENSE
reccd-1.0.3.dist-info/METADATA
reccd-1.0.3.dist-info/WHEEL
reccd-1.0.3.dist-info/entry_points.txt
reccd-1.0.3.dist-info/top_level.txt
reccd-1.0.3.dist-info/RECORD
